{
  "lastUpdated": "2026-04-19T18:08:56.786083",
  "period": "2026/03/20 - 2026/04/19",
  "pageViews": 267,
  "todayPageViews": 0,
  "users": 30,
  "todayUsers": 0,
  "sessions": 132,
  "todaySessions": 0,
  "clicks": {
    "amazon": 0,
    "rakuten": 0,
    "ofuse": 0
  },
  "todayClicks": {
    "amazon": 0,
    "rakuten": 0,
    "ofuse": 0
  },
  "shares": {
    "x": 0,
    "line": 0
  },
  "todayShares": {
    "x": 0,
    "line": 0
  },
  "topPages": [
    {
      "path": "/inclusive/editor-secret-dashboard/",
      "views": 130
    },
    {
      "path": "/inclusive/",
      "views": 81
    },
    {
      "path": "/inclusive/news/0063db5ff768/",
      "views": 15
    },
    {
      "path": "/inclusive/news/",
      "views": 13
    },
    {
      "path": "/inclusive/category/diverse-learning/",
      "views": 6
    },
    {
      "path": "/inclusive/category/policy/",
      "views": 4
    },
    {
      "path": "/inclusive/category/ict/",
      "views": 3
    },
    {
      "path": "/inclusive/category/support/",
      "views": 3
    },
    {
      "path": "/inclusive/bookmarks/",
      "views": 2
    },
    {
      "path": "/inclusive/news/56838966529c/",
      "views": 2
    }
  ]
}